{
  "schema": "machine-cycle-v1",
  "version": "1.0.0",
  "at": "2026-07-03T11:52:53Z",
  "ok": false,
  "loops": [
    {
      "loop_id": "LP-WORKER-EXEC",
      "name": "worker_execution",
      "ok": true,
      "receipt_path": "receipts/proof/worker-execution-gate-latest-v1.json",
      "at": "2026-07-03T11:51:40Z"
    },
    {
      "loop_id": "LP-MACHINE-VALID",
      "name": "machine_validation",
      "ok": true,
      "receipt_path": "receipts/proof/machine-validation-latest-v1.json",
      "at": "2026-07-03T11:52:53Z"
    },
    {
      "loop_id": "LP-ADVERSARIAL",
      "name": "adversarial_critique",
      "ok": true,
      "receipt_path": "receipts/proof/adversarial-critique-latest-v1.json",
      "at": "2026-07-03T11:52:53Z"
    },
    {
      "loop_id": "LP-SELF-REPAIR",
      "name": "self_repair",
      "ok": true,
      "receipt_path": "receipts/proof/self-repair-latest-v1.json",
      "at": "2026-07-03T11:51:41Z"
    },
    {
      "loop_id": "LP-OUTSIDE-AUDIT",
      "name": "outside_audit",
      "ok": true,
      "receipt_path": "receipts/proof/spine-live-probe-latest-v1.json",
      "at": "2026-07-03T11:51:41Z"
    },
    {
      "loop_id": "LP-RESEARCH",
      "name": "deep_research",
      "ok": false,
      "receipt_path": "receipts/proof/uncertainty-research-latest-v1.json",
      "at": ""
    },
    {
      "loop_id": "LP-RECEIPT-PROOF",
      "name": "receipt_proof",
      "ok": false,
      "receipt_path": "receipts/proof/machine-cycle-latest-v1.json",
      "at": "2026-07-03T11:52:03Z"
    },
    {
      "loop_id": "LP-EARNED-AUTONOMY",
      "name": "earned_autonomy",
      "ok": true,
      "receipt_path": "receipts/proof/founder-trigger-retirement-latest-v1.json",
      "at": "2026-07-03T11:51:41Z"
    }
  ],
  "founder_blocked_count": 0,
  "kaizen_pick": "kaizen_pick \u00b7 KZ-002 \u00b7 Kaizen queue motor \u2014 pick highest ROI machine_safe per cycle",
  "retirement_candidates_ready": [],
  "report_line": "machine_cycle PARTIAL \u00b7 6/8 loops green"
}
