{
  "plan_id": "CLOUD-SEC-086",
  "version": "secondary-cloud-forge-run-next-100-v1",
  "target": "sourcea/fbe-cloud-worker",
  "validation": "cloud_forge_incident_038",
  "metadata": {
    "core_capability": "competitor_evidence_pipeline",
    "client_problem_id": "P2-onboard-friction",
    "workstream": "ws-onboard",
    "competitor": "Inngest",
    "tier": "T2",
    "cost_tier": "free",
    "maps_registry": "sa-mkt-0086"
  },
  "inputs": {
    "plane": "cloud_forge",
    "action": "SOW snippet if services-led",
    "workstream": "ws-onboard",
    "tier": "T2",
    "competitor": "Inngest",
    "maps_registry": "sa-mkt-0086"
  },
  "outputs": {
    "artifact": "cloud_receipt",
    "receipt_url": "/receipts/cloud-dispatch/CLOUD-SEC-086.json"
  }
}
